{
  "parent": "minecraft:recipes/root",
  "criteria": {
    "has_the_recipe": {
      "conditions": {
        "recipe": "grass_craft:grass_tnt"
      },
      "trigger": "minecraft:recipe_unlocked"
    },
    "has_vanilla": {
      "conditions": {
        "items": [
          {
            "items": "grass_craft:vanilla"
          }
        ]
      },
      "trigger": "minecraft:inventory_changed"
    }
  },
  "requirements": [
    [
      "has_the_recipe",
      "has_vanilla"
    ]
  ],
  "rewards": {
    "recipes": [
      "grass_craft:grass_tnt"
    ]
  }
}